{
  "upcoming_matches": [
    {
      "id": "2872048",
      "time_obj": "2025-12-10T06:00:00",
      "home_team": "Canberra United (W)",
      "away_team": "Sydney FC (W)",
      "handicap": "0",
      "goal_line": "2.75",
      "time": "07:00"
    },
    {
      "id": "2907713",
      "time_obj": "2025-12-10T06:00:00",
      "home_team": "Mojosari Putra",
      "away_team": "Blayu FC",
      "handicap": "0.75",
      "goal_line": "3",
      "time": "07:00"
    },
    {
      "id": "2907863",
      "time_obj": "2025-12-10T08:00:00",
      "home_team": "Surat Thani City",
      "away_team": "Satun United",
      "handicap": "-0.25",
      "goal_line": "2.75",
      "time": "09:00"
    },
    {
      "id": "2907998",
      "time_obj": "2025-12-10T08:00:00",
      "home_team": "Aris Limassol  (W)",
      "away_team": "Lakatamia FC (W)",
      "handicap": "3",
      "goal_line": "4",
      "time": "09:00"
    },
    {
      "id": "2907714",
      "time_obj": "2025-12-10T08:00:00",
      "home_team": "Triples Kediri",
      "away_team": "Persema Malang",
      "handicap": "-0.5",
      "goal_line": "3.25",
      "time": "09:00"
    },
    {
      "id": "2907715",
      "time_obj": "2025-12-10T08:00:00",
      "home_team": "Gen B Kota Mojokerto",
      "away_team": "Akor FC Jombang",
      "handicap": "-0.5",
      "goal_line": "3.25",
      "time": "09:00"
    },
    {
      "id": "2907488",
      "time_obj": "2025-12-10T09:30:00",
      "home_team": "Fc Meshakhte Tkibuli",
      "away_team": "FC Telavi",
      "handicap": "-0.25",
      "goal_line": "2.25",
      "time": "10:30"
    },
    {
      "id": "2907703",
      "time_obj": "2025-12-10T09:30:00",
      "home_team": "Reliance FYC",
      "away_team": "Kalina Rangers",
      "handicap": "-0.25",
      "goal_line": "2.5",
      "time": "10:30"
    },
    {
      "id": "2860629",
      "time_obj": "2025-12-10T10:00:00",
      "home_team": "Hiroshima Sanfrecce",
      "away_team": "Shanghai Shenhua",
      "handicap": "1.5",
      "goal_line": "3",
      "time": "11:00"
    },
    {
      "id": "2860630",
      "time_obj": "2025-12-10T10:00:00",
      "home_team": "FC Seoul",
      "away_team": "Melbourne City",
      "handicap": "0.75",
      "goal_line": "2.5",
      "time": "11:00"
    },
    {
      "id": "2907304",
      "time_obj": "2025-12-10T10:00:00",
      "home_team": "Buxoro FK",
      "away_team": "Xorazm Urganch",
      "handicap": "0.25",
      "goal_line": "2.25",
      "time": "11:00"
    },
    {
      "id": "2908004",
      "time_obj": "2025-12-10T10:00:00",
      "home_team": "Aliaga Futbol AS U19",
      "away_team": "Manisa Belediyespor U19",
      "handicap": "-0.25",
      "goal_line": "3.25",
      "time": "11:00"
    },
    {
      "id": "2815048",
      "time_obj": "2025-12-10T10:00:00",
      "home_team": "UE Santa Coloma",
      "away_team": "Ranger's FC",
      "handicap": "0.25",
      "goal_line": "2.25",
      "time": "11:00"
    },
    {
      "id": "2871979",
      "time_obj": "2025-12-10T10:00:00",
      "home_team": "Qarabag U19",
      "away_team": "Ajax U19",
      "handicap": "-3.25",
      "goal_line": "4.5",
      "time": "11:00"
    },
    {
      "id": "2906215",
      "time_obj": "2025-12-10T10:00:00",
      "home_team": "E Nel G Tick",
      "away_team": "Cəbrayıl FK",
      "handicap": "0.5",
      "goal_line": "2.75",
      "time": "11:00"
    },
    {
      "id": "2908002",
      "time_obj": "2025-12-10T10:00:00",
      "home_team": "FC Metalist 1925 (W)",
      "away_team": "Kolos Kovalivka (W)",
      "handicap": "1.5",
      "goal_line": "3",
      "time": "11:00"
    },
    {
      "id": "2906214",
      "time_obj": "2025-12-10T10:30:00",
      "home_team": "Baku Sporting",
      "away_team": "Shahdagh Qusar",
      "handicap": "0.5",
      "goal_line": "2.5",
      "time": "11:30"
    },
    {
      "id": "2906216",
      "time_obj": "2025-12-10T10:30:00",
      "home_team": "FK MOIK Baku",
      "away_team": "Simal FK",
      "handicap": "1.75",
      "goal_line": "3.25",
      "time": "11:30"
    },
    {
      "id": "2907868",
      "time_obj": "2025-12-10T11:00:00",
      "home_team": "Beyoglu Yeni Carsi FK U19",
      "away_team": "Erokspor U19",
      "handicap": "-0.75",
      "goal_line": "2.75",
      "time": "12:00"
    },
    {
      "id": "2838035",
      "time_obj": "2025-12-10T11:00:00",
      "home_team": "Chainat FC",
      "away_team": "Songkhla FC",
      "handicap": "0.5",
      "goal_line": "2.25",
      "time": "12:00"
    },
    {
      "id": "2871974",
      "time_obj": "2025-12-10T11:00:00",
      "home_team": "Benfica U19",
      "away_team": "Napoli(U19)",
      "handicap": "2.5",
      "goal_line": "3.75",
      "time": "12:00"
    },
    {
      "id": "2871981",
      "time_obj": "2025-12-10T11:00:00",
      "home_team": "Villarreal U19",
      "away_team": "FC Kobenhavn U19",
      "handicap": "0.5",
      "goal_line": "3",
      "time": "12:00"
    },
    {
      "id": "2908006",
      "time_obj": "2025-12-10T11:00:00",
      "home_team": "Fostiras Kaisarianis (W)",
      "away_team": "AE Mykonou (W)",
      "handicap": "-1",
      "goal_line": "3.25",
      "time": "12:00"
    },
    {
      "id": "2907756",
      "time_obj": "2025-12-10T11:00:00",
      "home_team": "Shillong Lajong Reserves",
      "away_team": "Meghalaya Police",
      "handicap": "0.75",
      "goal_line": "2.75",
      "time": "12:00"
    },
    {
      "id": "2901670",
      "time_obj": "2025-12-10T11:30:00",
      "home_team": "Singapore (W)(N)",
      "away_team": "Thailand (W)",
      "handicap": "-7.5",
      "goal_line": "8",
      "time": "12:30"
    },
    {
      "id": "2906646",
      "time_obj": "2025-12-10T11:30:00",
      "home_team": "FK Graffin Vlasim(N)",
      "away_team": "Zlate Moravce",
      "handicap": "0.25",
      "goal_line": "3.25",
      "time": "12:30"
    },
    {
      "id": "2908051",
      "time_obj": "2025-12-10T11:30:00",
      "home_team": "Al Hussein",
      "away_team": "Karbalaa",
      "handicap": "0.25",
      "goal_line": "1.75",
      "time": "12:30"
    },
    {
      "id": "2908052",
      "time_obj": "2025-12-10T11:30:00",
      "home_team": "Kadhimiya SC",
      "away_team": "Afak SC",
      "handicap": "0.5",
      "goal_line": "1.75",
      "time": "12:30"
    },
    {
      "id": "2885570",
      "time_obj": "2025-12-10T11:55:00",
      "home_team": "AL-jeel",
      "away_team": "Jerash FC",
      "handicap": "0.5",
      "goal_line": "2.25",
      "time": "12:55"
    },
    {
      "id": "2839036",
      "time_obj": "2025-12-10T12:00:00",
      "home_team": "Estoril U23",
      "away_team": "Uniao Leiria U23",
      "handicap": "0.25",
      "goal_line": "2.75",
      "time": "13:00"
    },
    {
      "id": "2905736",
      "time_obj": "2025-12-10T12:00:00",
      "home_team": "Iraq U23(N)",
      "away_team": "United Arab Emirates U23",
      "handicap": "0.25",
      "goal_line": "2.25",
      "time": "13:00"
    },
    {
      "id": "2905737",
      "time_obj": "2025-12-10T12:00:00",
      "home_team": "Oman U23(N)",
      "away_team": "Yemen U23",
      "handicap": "0",
      "goal_line": "2.25",
      "time": "13:00"
    },
    {
      "id": "2819946",
      "time_obj": "2025-12-10T12:00:00",
      "home_team": "OFK Petrovac",
      "away_team": "Bokelj Kotor",
      "handicap": "1",
      "goal_line": "2.5",
      "time": "13:00"
    },
    {
      "id": "2907489",
      "time_obj": "2025-12-10T12:00:00",
      "home_team": "Gareji Sagarejo",
      "away_team": "Spaeri FC",
      "handicap": "0.5",
      "goal_line": "2.25",
      "time": "13:00"
    },
    {
      "id": "2907869",
      "time_obj": "2025-12-10T12:00:00",
      "home_team": "Bursaspor U19",
      "away_team": "Yael U19",
      "handicap": "1.25",
      "goal_line": "3",
      "time": "13:00"
    },
    {
      "id": "2907870",
      "time_obj": "2025-12-10T12:00:00",
      "home_team": "Sakaryaspor U19",
      "away_team": "Istanbulspor U19",
      "handicap": "0.25",
      "goal_line": "2.75",
      "time": "13:00"
    },
    {
      "id": "2907873",
      "time_obj": "2025-12-10T12:00:00",
      "home_team": "Pendikspor U19",
      "away_team": "Umraniyespor U19",
      "handicap": "0.75",
      "goal_line": "3",
      "time": "13:00"
    },
    {
      "id": "2871973",
      "time_obj": "2025-12-10T12:00:00",
      "home_team": "Bilbao U19",
      "away_team": "Paris Saint Germain U19",
      "handicap": "0.25",
      "goal_line": "3.25",
      "time": "13:00"
    },
    {
      "id": "2906225",
      "time_obj": "2025-12-10T12:00:00",
      "home_team": "FK Rudar Pljevlja",
      "away_team": "FK Podgorica",
      "handicap": "0.75",
      "goal_line": "2.75",
      "time": "13:00"
    },
    {
      "id": "2908046",
      "time_obj": "2025-12-10T12:00:00",
      "home_team": "FC Robo (W)",
      "away_team": "Delta Queens (W)",
      "handicap": "1.5",
      "goal_line": "2.75",
      "time": "13:00"
    },
    {
      "id": "2860775",
      "time_obj": "2025-12-10T12:15:00",
      "home_team": "Persib Bandung",
      "away_team": "Bangkok United FC",
      "handicap": "0.75",
      "goal_line": "2.75",
      "time": "13:15"
    },
    {
      "id": "2860776",
      "time_obj": "2025-12-10T12:15:00",
      "home_team": "Selangor",
      "away_team": "Lion City Sailors",
      "handicap": "-1",
      "goal_line": "3.25",
      "time": "13:15"
    },
    {
      "id": "2908008",
      "time_obj": "2025-12-10T12:30:00",
      "home_team": "Al-Arabi(JOR)",
      "away_team": "Maan",
      "handicap": "0.5",
      "goal_line": "2",
      "time": "13:30"
    },
    {
      "id": "2908009",
      "time_obj": "2025-12-10T12:30:00",
      "home_team": "Dogra FC",
      "away_team": "Ethad Al-Ramtha",
      "handicap": "0.75",
      "goal_line": "2",
      "time": "13:30"
    },
    {
      "id": "2908010",
      "time_obj": "2025-12-10T12:30:00",
      "home_team": "Kufer Soom",
      "away_team": "Jerash Club",
      "handicap": "-1",
      "goal_line": "2.5",
      "time": "13:30"
    },
    {
      "id": "2908013",
      "time_obj": "2025-12-10T12:30:00",
      "home_team": "Al Yarmouk",
      "away_team": "Sama SC",
      "handicap": "0",
      "goal_line": "2.25",
      "time": "13:30"
    },
    {
      "id": "2907989",
      "time_obj": "2025-12-10T12:30:00",
      "home_team": "Nabrouh",
      "away_team": "Sed Elmahla",
      "handicap": "1",
      "goal_line": "2",
      "time": "13:30"
    },
    {
      "id": "2901767",
      "time_obj": "2025-12-10T12:30:00",
      "home_team": "Midtjylland U19",
      "away_team": "Koln U19",
      "handicap": "0.75",
      "goal_line": "3",
      "time": "13:30"
    },
    {
      "id": "2907774",
      "time_obj": "2025-12-10T12:30:00",
      "home_team": "Moyale Barracks",
      "away_team": "Big Bullets FC",
      "handicap": "-0.75",
      "goal_line": "2.25",
      "time": "13:30"
    },
    {
      "id": "2907864",
      "time_obj": "2025-12-10T12:30:00",
      "home_team": "Lykoi Haidariou",
      "away_team": "FC Sourmena",
      "handicap": "-0.25",
      "goal_line": "2.25",
      "time": "13:30"
    },
    {
      "id": "2907865",
      "time_obj": "2025-12-10T12:45:00",
      "home_team": "OFI FC (W)",
      "away_team": "AO Rea (W)",
      "handicap": "0.75",
      "goal_line": "2.75",
      "time": "13:45"
    },
    {
      "id": "2895609",
      "time_obj": "2025-12-10T13:00:00",
      "home_team": "Aluminium Arak",
      "away_team": "Sepahan",
      "handicap": "-0.5",
      "goal_line": "1.75",
      "time": "14:00"
    },
    {
      "id": "2819943",
      "time_obj": "2025-12-10T13:00:00",
      "home_team": "Arsenal Tivat",
      "away_team": "Jedinstvo Bijelo Polje",
      "handicap": "0.5",
      "goal_line": "2.25",
      "time": "14:00"
    },
    {
      "id": "2819945",
      "time_obj": "2025-12-10T13:00:00",
      "home_team": "Jezero Plav",
      "away_team": "FK Buducnost Podgorica",
      "handicap": "-0.25",
      "goal_line": "2.25",
      "time": "14:00"
    },
    {
      "id": "2851124",
      "time_obj": "2025-12-10T13:00:00",
      "home_team": "Randers Freja U19",
      "away_team": "Aarhus AGF U19",
      "handicap": "0",
      "goal_line": "3.25",
      "time": "14:00"
    },
    {
      "id": "2871975",
      "time_obj": "2025-12-10T13:00:00",
      "home_team": "Club Brugge U19",
      "away_team": "Arsenal U19",
      "handicap": "1.5",
      "goal_line": "3.75",
      "time": "14:00"
    },
    {
      "id": "2871978",
      "time_obj": "2025-12-10T13:00:00",
      "home_team": "Bayer Leverkusen U19",
      "away_team": "Newcastle U19",
      "handicap": "0.25",
      "goal_line": "3.25",
      "time": "14:00"
    },
    {
      "id": "2901768",
      "time_obj": "2025-12-10T13:00:00",
      "home_team": "Dinamo Tbilisi U19",
      "away_team": "Dinamo Minsk U19",
      "handicap": "0.5",
      "goal_line": "2.5",
      "time": "14:00"
    },
    {
      "id": "2907985",
      "time_obj": "2025-12-10T13:00:00",
      "home_team": "Sesvete U19",
      "away_team": "HNK Sibenik U19",
      "handicap": "3",
      "goal_line": "4",
      "time": "14:00"
    },
    {
      "id": "2907872",
      "time_obj": "2025-12-10T13:00:00",
      "home_team": "Orlando Pirates B FC",
      "away_team": "Mike-1-Stars FC",
      "handicap": "0.25",
      "goal_line": "2",
      "time": "14:00"
    },
    {
      "id": "2906217",
      "time_obj": "2025-12-10T13:00:00",
      "home_team": "Buhimba United Saints FC",
      "away_team": "defense forces",
      "handicap": "0",
      "goal_line": "2.75",
      "time": "14:00"
    },
    {
      "id": "2906218",
      "time_obj": "2025-12-10T13:00:00",
      "home_team": "Lugazi Municipal FC",
      "away_team": "Uganda Police FC",
      "handicap": "-0.5",
      "goal_line": "2.25",
      "time": "14:00"
    },
    {
      "id": "2907866",
      "time_obj": "2025-12-10T13:00:00",
      "home_team": "AE Kifisias (W)",
      "away_team": "Odysseas Moschatou (W)",
      "handicap": "-0.25",
      "goal_line": "2.75",
      "time": "14:00"
    },
    {
      "id": "2908005",
      "time_obj": "2025-12-10T13:00:00",
      "home_team": "Pyrgos AFC (W)",
      "away_team": "Asteras Tripolis (W)",
      "handicap": "-4.5",
      "goal_line": "5.5",
      "time": "14:00"
    },
    {
      "id": "2895611",
      "time_obj": "2025-12-10T13:45:00",
      "home_team": "Esteghlal Tehran",
      "away_team": "Malavan",
      "handicap": "0.5",
      "goal_line": "2",
      "time": "14:45"
    },
    {
      "id": "2809130",
      "time_obj": "2025-12-10T14:00:00",
      "home_team": "Recreativo Huelva",
      "away_team": "UCAM Murcia",
      "handicap": "0.25",
      "goal_line": "2",
      "time": "15:00"
    },
    {
      "id": "2893963",
      "time_obj": "2025-12-10T14:00:00",
      "home_team": "MFK Ruzomberok",
      "away_team": "FK Kosice",
      "handicap": "0.25",
      "goal_line": "2.5",
      "time": "15:00"
    },
    {
      "id": "2819944",
      "time_obj": "2025-12-10T14:00:00",
      "home_team": "Decic Tuzi",
      "away_team": "FK Mladost DG",
      "handicap": "0.5",
      "goal_line": "2.25",
      "time": "15:00"
    },
    {
      "id": "2815044",
      "time_obj": "2025-12-10T14:00:00",
      "home_team": "Atletic Club D Escaldes",
      "away_team": "CF Esperanca dAndorra",
      "handicap": "2.25",
      "goal_line": "3",
      "time": "15:00"
    },
    {
      "id": "2871977",
      "time_obj": "2025-12-10T14:00:00",
      "home_team": "Juventus U19",
      "away_team": "Paphos U19",
      "handicap": "3.25",
      "goal_line": "4",
      "time": "15:00"
    },
    {
      "id": "2907991",
      "time_obj": "2025-12-10T14:00:00",
      "home_team": "Doma United",
      "away_team": "Sokoto United FC",
      "handicap": "1",
      "goal_line": "2.25",
      "time": "15:00"
    },
    {
      "id": "2807365",
      "time_obj": "2025-12-10T14:30:00",
      "home_team": "UD Marbella",
      "away_team": "Atletico de Madrid B",
      "handicap": "-0.25",
      "goal_line": "2",
      "time": "15:30"
    },
    {
      "id": "2859810",
      "time_obj": "2025-12-10T15:00:00",
      "home_team": "Plateau United",
      "away_team": "Rivers United",
      "handicap": "0.5",
      "goal_line": "2",
      "time": "16:00"
    },
    {
      "id": "2819947",
      "time_obj": "2025-12-10T15:00:00",
      "home_team": "FK Sutjeska Niksic",
      "away_team": "FK Mornar Bar",
      "handicap": "0.25",
      "goal_line": "2.5",
      "time": "16:00"
    },
    {
      "id": "2906222",
      "time_obj": "2025-12-10T15:00:00",
      "home_team": "FC Iberia 1999 Tbilisi",
      "away_team": "Dila Gori",
      "handicap": "0",
      "goal_line": "2.25",
      "time": "16:00"
    },
    {
      "id": "2871976",
      "time_obj": "2025-12-10T15:00:00",
      "home_team": "Borussia Dortmund U19",
      "away_team": "Bodo Glimt U19",
      "handicap": "3.75",
      "goal_line": "4.75",
      "time": "16:00"
    },
    {
      "id": "2871980",
      "time_obj": "2025-12-10T15:00:00",
      "home_team": "Real Madrid U19",
      "away_team": "Manchester City U19",
      "handicap": "0.25",
      "goal_line": "3.25",
      "time": "16:00"
    },
    {
      "id": "2901769",
      "time_obj": "2025-12-10T15:00:00",
      "home_team": "Real Betis U19",
      "away_team": "FC Porto U19",
      "handicap": "0.5",
      "goal_line": "3",
      "time": "16:00"
    },
    {
      "id": "2907992",
      "time_obj": "2025-12-10T15:00:00",
      "home_team": "Abia Angels FC (W)",
      "away_team": "Osun Babes (W)",
      "handicap": "0.25",
      "goal_line": "2.25",
      "time": "16:00"
    },
    {
      "id": "2876414",
      "time_obj": "2025-12-10T15:00:00",
      "home_team": "Talaea EI-Gaish",
      "away_team": "Ceramica Cleopatra FC",
      "handicap": "-0.5",
      "goal_line": "2.5",
      "time": "16:00"
    },
    {
      "id": "2907986",
      "time_obj": "2025-12-10T15:30:00",
      "home_team": "Al Wahda(UAE)",
      "away_team": "Al-Nassr",
      "handicap": "-1.25",
      "goal_line": "3.25",
      "time": "16:30"
    },
    {
      "id": "2901770",
      "time_obj": "2025-12-10T15:30:00",
      "home_team": "Puskas Akademia Fehervar U19",
      "away_team": "Steaua Bucuresti U19",
      "handicap": "0.5",
      "goal_line": "2.5",
      "time": "16:30"
    },
    {
      "id": "2901771",
      "time_obj": "2025-12-10T15:30:00",
      "home_team": "MSK Zilina U19",
      "away_team": "Red Star Belgrade U19",
      "handicap": "0",
      "goal_line": "3.25",
      "time": "16:30"
    },
    {
      "id": "2861934",
      "time_obj": "2025-12-10T16:00:00",
      "home_team": "Al-Baq's",
      "away_team": "Ramtha Club",
      "handicap": "0.25",
      "goal_line": "2.25",
      "time": "17:00"
    },
    {
      "id": "2901772",
      "time_obj": "2025-12-10T16:00:00",
      "home_team": "Nantes U19",
      "away_team": "Maccabi Haifa U19",
      "handicap": "0.75",
      "goal_line": "3",
      "time": "17:00"
    },
    {
      "id": "2907996",
      "time_obj": "2025-12-10T16:00:00",
      "home_team": "Auxerre W",
      "away_team": "Reims (W)",
      "handicap": "1",
      "goal_line": "2.75",
      "time": "17:00"
    },
    {
      "id": "2907993",
      "time_obj": "2025-12-10T16:00:00",
      "home_team": "Al Merreikh",
      "away_team": "Marines FC",
      "handicap": "0.5",
      "goal_line": "2.25",
      "time": "17:00"
    },
    {
      "id": "2906141",
      "time_obj": "2025-12-10T16:00:00",
      "home_team": "Real Bamako",
      "away_team": "Stade Malien de Bamako",
      "handicap": "-0.25",
      "goal_line": "1.75",
      "time": "17:00"
    },
    {
      "id": "2907871",
      "time_obj": "2025-12-10T16:00:00",
      "home_team": "NS Mura (W)",
      "away_team": "Olimpija Ljubljana (W)",
      "handicap": "4",
      "goal_line": "5",
      "time": "17:00"
    },
    {
      "id": "2907988",
      "time_obj": "2025-12-10T16:00:00",
      "home_team": "Unique Global FC",
      "away_team": "Tallinding United",
      "handicap": "0",
      "goal_line": "2",
      "time": "17:00"
    },
    {
      "id": "2908007",
      "time_obj": "2025-12-10T16:00:00",
      "home_team": "Sibanor United",
      "away_team": "Baalor Sarr FC",
      "handicap": "0",
      "goal_line": "1.75",
      "time": "17:00"
    },
    {
      "id": "2907982",
      "time_obj": "2025-12-10T16:15:00",
      "home_team": "Freetown City",
      "away_team": "Freetonians SLIFA",
      "handicap": "0",
      "goal_line": "1.75",
      "time": "17:15"
    },
    {
      "id": "2793136",
      "time_obj": "2025-12-10T17:00:00",
      "home_team": "Stade Ouchy",
      "away_team": "Neuchatel Xamax",
      "handicap": "0.75",
      "goal_line": "3",
      "time": "18:00"
    },
    {
      "id": "2904050",
      "time_obj": "2025-12-10T17:00:00",
      "home_team": "Ravenna",
      "away_team": "Renate AC",
      "handicap": "1",
      "goal_line": "2.25",
      "time": "18:00"
    },
    {
      "id": "2904051",
      "time_obj": "2025-12-10T17:00:00",
      "home_team": "Potenza",
      "away_team": "Crotone",
      "handicap": "0",
      "goal_line": "2.25",
      "time": "18:00"
    },
    {
      "id": "2904052",
      "time_obj": "2025-12-10T17:00:00",
      "home_team": "Pro Vercelli",
      "away_team": "Latina",
      "handicap": "0.5",
      "goal_line": "2.25",
      "time": "18:00"
    },
    {
      "id": "2904053",
      "time_obj": "2025-12-10T17:00:00",
      "home_team": "Ternana",
      "away_team": "Brescia",
      "handicap": "0",
      "goal_line": "2",
      "time": "18:00"
    },
    {
      "id": "2907701",
      "time_obj": "2025-12-10T17:00:00",
      "home_team": "Sparta Praha B",
      "away_team": "Aritma Praha",
      "handicap": "1",
      "goal_line": "3.5",
      "time": "18:00"
    },
    {
      "id": "2874264",
      "time_obj": "2025-12-10T17:00:00",
      "home_team": "Pieta Hotspurs",
      "away_team": "St. Andrews",
      "handicap": "1",
      "goal_line": "2.75",
      "time": "18:00"
    },
    {
      "id": "2901773",
      "time_obj": "2025-12-10T17:00:00",
      "home_team": "KRC Genk U19",
      "away_team": "HJK Helsinki U19",
      "handicap": "1.25",
      "goal_line": "2.75",
      "time": "18:00"
    },
    {
      "id": "2907990",
      "time_obj": "2025-12-10T17:00:00",
      "home_team": "Aguilas Teotihuacan",
      "away_team": "Atletico Huejutla",
      "handicap": "0.25",
      "goal_line": "3.25",
      "time": "18:00"
    },
    {
      "id": "2905338",
      "time_obj": "2025-12-10T17:00:00",
      "home_team": "CDSyC Cruz Azul(N)",
      "away_team": "Flamengo",
      "handicap": "-1",
      "goal_line": "2.5",
      "time": "18:00"
    },
    {
      "id": "2874265",
      "time_obj": "2025-12-10T17:15:00",
      "home_team": "Fgura United",
      "away_team": "Balzan FC",
      "handicap": "-1",
      "goal_line": "3",
      "time": "18:15"
    },
    {
      "id": "2861161",
      "time_obj": "2025-12-10T17:45:00",
      "home_team": "Villarreal",
      "away_team": "FC Copenhagen",
      "handicap": "1.25",
      "goal_line": "3",
      "time": "18:45"
    },
    {
      "id": "2861189",
      "time_obj": "2025-12-10T17:45:00",
      "home_team": "Qarabag",
      "away_team": "AFC Ajax",
      "handicap": "0.25",
      "goal_line": "2.75",
      "time": "18:45"
    },
    {
      "id": "2884800",
      "time_obj": "2025-12-10T17:45:00",
      "home_team": "Barcelona (W)",
      "away_team": "SL Benfica (W)",
      "handicap": "4.5",
      "goal_line": "5.5",
      "time": "18:45"
    },
    {
      "id": "2884801",
      "time_obj": "2025-12-10T17:45:00",
      "home_team": "Valerenga (W)",
      "away_team": "Paris FC (W)",
      "handicap": "0",
      "goal_line": "2.75",
      "time": "18:45"
    },
    {
      "id": "2813272",
      "time_obj": "2025-12-10T18:00:00",
      "home_team": "Hertha Zehlendorf",
      "away_team": "BSG Chemie Leipzig",
      "handicap": "0",
      "goal_line": "2.75",
      "time": "19:00"
    },
    {
      "id": "2906140",
      "time_obj": "2025-12-10T18:00:00",
      "home_team": "Afrique Football Elite",
      "away_team": "Djoliba",
      "handicap": "-0.5",
      "goal_line": "1.75",
      "time": "19:00"
    },
    {
      "id": "2908020",
      "time_obj": "2025-12-10T18:00:00",
      "home_team": "Fundacio Esportiva Grama",
      "away_team": "Terrassa",
      "handicap": "-0.25",
      "goal_line": "2.25",
      "time": "19:00"
    },
    {
      "id": "2876435",
      "time_obj": "2025-12-10T18:00:00",
      "home_team": "Ismaily",
      "away_team": "El Gouna FC",
      "handicap": "0",
      "goal_line": "2.25",
      "time": "19:00"
    },
    {
      "id": "2876456",
      "time_obj": "2025-12-10T18:00:00",
      "home_team": "ZED FC(N)",
      "away_team": "Smouha SC",
      "handicap": "-1",
      "goal_line": "3",
      "time": "19:00"
    },
    {
      "id": "2823758",
      "time_obj": "2025-12-10T18:30:00",
      "home_team": "Nurnberg (W)",
      "away_team": "Eintracht Frankfurt (W)",
      "handicap": "-2.25",
      "goal_line": "3.75",
      "time": "19:30"
    },
    {
      "id": "2871395",
      "time_obj": "2025-12-10T19:00:00",
      "home_team": "Vitesse Arnhem",
      "away_team": "RKC Waalwijk",
      "handicap": "0",
      "goal_line": "3.25",
      "time": "20:00"
    },
    {
      "id": "2907480",
      "time_obj": "2025-12-10T19:00:00",
      "home_team": "Blooming",
      "away_team": "Aurora",
      "handicap": "1.25",
      "goal_line": "3.5",
      "time": "20:00"
    },
    {
      "id": "2840100",
      "time_obj": "2025-12-10T19:00:00",
      "home_team": "Cazalegas",
      "away_team": "CD Villacanas",
      "handicap": "-0.75",
      "goal_line": "2.25",
      "time": "20:00"
    },
    {
      "id": "2857392",
      "time_obj": "2025-12-10T19:00:00",
      "home_team": "Coventry U21",
      "away_team": "Watford U21",
      "handicap": "0.25",
      "goal_line": "3.75",
      "time": "20:00"
    },
    {
      "id": "2901774",
      "time_obj": "2025-12-10T19:00:00",
      "home_team": "Hibernian U19",
      "away_team": "Dinamo KyivU19",
      "handicap": "-0.75",
      "goal_line": "2.75",
      "time": "20:00"
    },
    {
      "id": "2908021",
      "time_obj": "2025-12-10T19:00:00",
      "home_team": "CF Montanesa",
      "away_team": "Sant Andreu",
      "handicap": "1.5",
      "goal_line": "2.5",
      "time": "20:00"
    },
    {
      "id": "2848277",
      "time_obj": "2025-12-10T19:30:00",
      "home_team": "Beti Kozkor KE",
      "away_team": "Aoiz",
      "handicap": "0.25",
      "goal_line": "2.5",
      "time": "20:30"
    },
    {
      "id": "2874266",
      "time_obj": "2025-12-10T19:30:00",
      "home_team": "Swieqi United",
      "away_team": "Marsa",
      "handicap": "0.75",
      "goal_line": "3",
      "time": "20:30"
    },
    {
      "id": "2907995",
      "time_obj": "2025-12-10T19:30:00",
      "home_team": "Willand Rovers",
      "away_team": "Mousehole",
      "handicap": "0",
      "goal_line": "3",
      "time": "20:30"
    },
    {
      "id": "2830461",
      "time_obj": "2025-12-10T19:30:00",
      "home_team": "Oud-Heverlee Leuven B",
      "away_team": "Hasselt",
      "handicap": "-1",
      "goal_line": "3",
      "time": "20:30"
    },
    {
      "id": "2854073",
      "time_obj": "2025-12-10T19:30:00",
      "home_team": "Brighton U21",
      "away_team": "Real Sociedad B",
      "handicap": "-0.5",
      "goal_line": "3",
      "time": "20:30"
    },
    {
      "id": "2805871",
      "time_obj": "2025-12-10T19:30:00",
      "home_team": "Newport City",
      "away_team": "Cardiff Draconians FC",
      "handicap": "0.5",
      "goal_line": "3",
      "time": "20:30"
    },
    {
      "id": "2906197",
      "time_obj": "2025-12-10T19:30:00",
      "home_team": "Cwmbran Celtic",
      "away_team": "Llantwit Major",
      "handicap": "-1.25",
      "goal_line": "2.75",
      "time": "20:30"
    },
    {
      "id": "2806281",
      "time_obj": "2025-12-10T19:30:00",
      "home_team": "Buckley Town",
      "away_team": "Gresford",
      "handicap": "1",
      "goal_line": "3.5",
      "time": "20:30"
    },
    {
      "id": "2798243",
      "time_obj": "2025-12-10T19:45:00",
      "home_team": "Bristol City",
      "away_team": "Leicester City",
      "handicap": "0.25",
      "goal_line": "2.5",
      "time": "20:45"
    },
    {
      "id": "2798244",
      "time_obj": "2025-12-10T19:45:00",
      "home_team": "Derby County",
      "away_team": "Millwall",
      "handicap": "0",
      "goal_line": "2",
      "time": "20:45"
    },
    {
      "id": "2798245",
      "time_obj": "2025-12-10T19:45:00",
      "home_team": "Ipswich Town",
      "away_team": "Stoke City",
      "handicap": "0.75",
      "goal_line": "2.5",
      "time": "20:45"
    },
    {
      "id": "2797678",
      "time_obj": "2025-12-10T19:45:00",
      "home_team": "Rotherham United",
      "away_team": "Blackpool",
      "handicap": "0.25",
      "goal_line": "2.25",
      "time": "20:45"
    },
    {
      "id": "2798783",
      "time_obj": "2025-12-10T19:45:00",
      "home_team": "Oldham Athletic",
      "away_team": "Walsall",
      "handicap": "0",
      "goal_line": "2.25",
      "time": "20:45"
    },
    {
      "id": "2798786",
      "time_obj": "2025-12-10T19:45:00",
      "home_team": "Crewe Alexandra",
      "away_team": "Newport County",
      "handicap": "0.75",
      "goal_line": "2.75",
      "time": "20:45"
    },
    {
      "id": "2818081",
      "time_obj": "2025-12-10T19:45:00",
      "home_team": "Carlisle United",
      "away_team": "Woking",
      "handicap": "1",
      "goal_line": "2.75",
      "time": "20:45"
    },
    {
      "id": "2820252",
      "time_obj": "2025-12-10T19:45:00",
      "home_team": "Kings Lynn",
      "away_team": "Macclesfield Town",
      "handicap": "0",
      "goal_line": "2.75",
      "time": "20:45"
    },
    {
      "id": "2831925",
      "time_obj": "2025-12-10T19:45:00",
      "home_team": "Havant Waterlooville",
      "away_team": "Bracknell Town",
      "handicap": "0.25",
      "goal_line": "3",
      "time": "20:45"
    },
    {
      "id": "2832019",
      "time_obj": "2025-12-10T19:45:00",
      "home_team": "Gosport Borough",
      "away_team": "Hanwell Town",
      "handicap": "0.5",
      "goal_line": "2.75",
      "time": "20:45"
    },
    {
      "id": "2828277",
      "time_obj": "2025-12-10T19:45:00",
      "home_team": "Stocksbridge Park Steels",
      "away_team": "FC United of Manchester",
      "handicap": "-0.5",
      "goal_line": "2.5",
      "time": "20:45"
    },
    {
      "id": "2898824",
      "time_obj": "2025-12-10T19:45:00",
      "home_team": "Tranent Juniors(N)",
      "away_team": "Inverness",
      "handicap": "-1.75",
      "goal_line": "3.25",
      "time": "20:45"
    },
    {
      "id": "2874267",
      "time_obj": "2025-12-10T19:45:00",
      "home_team": "Mgarr United FC",
      "away_team": "Melita FC Saint Julian",
      "handicap": "-0.25",
      "goal_line": "2.75",
      "time": "20:45"
    },
    {
      "id": "2907997",
      "time_obj": "2025-12-10T19:45:00",
      "home_team": "Frome Town",
      "away_team": "Swindon Supermarine",
      "handicap": "0.75",
      "goal_line": "2.75",
      "time": "20:45"
    },
    {
      "id": "2907994",
      "time_obj": "2025-12-10T19:45:00",
      "home_team": "Heaton Stannington",
      "away_team": "Grimsby Borough",
      "handicap": "0.25",
      "goal_line": "2.5",
      "time": "20:45"
    },
    {
      "id": "2906203",
      "time_obj": "2025-12-10T19:45:00",
      "home_team": "Stirling University",
      "away_team": "Clydebank FC",
      "handicap": "-1.5",
      "goal_line": "3.75",
      "time": "20:45"
    },
    {
      "id": "2903992",
      "time_obj": "2025-12-10T19:45:00",
      "home_team": "AC Juvenes",
      "away_team": "Tre Penne",
      "handicap": "-0.5",
      "goal_line": "2.5",
      "time": "20:45"
    },
    {
      "id": "2861070",
      "time_obj": "2025-12-10T20:00:00",
      "home_team": "Real Madrid",
      "away_team": "Manchester City",
      "handicap": "-0.25",
      "goal_line": "3.25",
      "time": "21:00"
    },
    {
      "id": "2861081",
      "time_obj": "2025-12-10T20:00:00",
      "home_team": "Athletic Bilbao",
      "away_team": "Paris Saint Germain (PSG)",
      "handicap": "-0.75",
      "goal_line": "2.75",
      "time": "21:00"
    },
    {
      "id": "2861120",
      "time_obj": "2025-12-10T20:00:00",
      "home_team": "Borussia Dortmund",
      "away_team": "Bodo Glimt",
      "handicap": "1.75",
      "goal_line": "3.5",
      "time": "21:00"
    },
    {
      "id": "2861133",
      "time_obj": "2025-12-10T20:00:00",
      "home_team": "Club Brugge",
      "away_team": "Arsenal",
      "handicap": "-1.25",
      "goal_line": "3",
      "time": "21:00"
    },
    {
      "id": "2861145",
      "time_obj": "2025-12-10T20:00:00",
      "home_team": "Bayer Leverkusen",
      "away_team": "Newcastle United",
      "handicap": "-0.25",
      "goal_line": "2.75",
      "time": "21:00"
    },
    {
      "id": "2861151",
      "time_obj": "2025-12-10T20:00:00",
      "home_team": "Benfica",
      "away_team": "Napoli",
      "handicap": "0",
      "goal_line": "2.25",
      "time": "21:00"
    },
    {
      "id": "2861165",
      "time_obj": "2025-12-10T20:00:00",
      "home_team": "Juventus",
      "away_team": "AEP Paphos",
      "handicap": "2.25",
      "goal_line": "3.25",
      "time": "21:00"
    },
    {
      "id": "2798246",
      "time_obj": "2025-12-10T20:00:00",
      "home_team": "Hull City",
      "away_team": "Wrexham",
      "handicap": "0.25",
      "goal_line": "2.5",
      "time": "21:00"
    },
    {
      "id": "2884802",
      "time_obj": "2025-12-10T20:00:00",
      "home_team": "Atletico de Madrid (W)",
      "away_team": "Bayern Munchen (W)",
      "handicap": "-0.5",
      "goal_line": "3",
      "time": "21:00"
    },
    {
      "id": "2884803",
      "time_obj": "2025-12-10T20:00:00",
      "home_team": "Chelsea FC (W)",
      "away_team": "AS Roma (W)",
      "handicap": "3",
      "goal_line": "4",
      "time": "21:00"
    },
    {
      "id": "2884804",
      "time_obj": "2025-12-10T20:00:00",
      "home_team": "Manchester United (W)",
      "away_team": "Lyon (W)",
      "handicap": "-1.25",
      "goal_line": "3.25",
      "time": "21:00"
    },
    {
      "id": "2905722",
      "time_obj": "2025-12-10T20:00:00",
      "home_team": "Club Aurora",
      "away_team": "Malacateco",
      "handicap": "0.25",
      "goal_line": "2.5",
      "time": "21:00"
    },
    {
      "id": "2908019",
      "time_obj": "2025-12-10T20:00:00",
      "home_team": "UE Cornella",
      "away_team": "Sabadell",
      "handicap": "-0.75",
      "goal_line": "2.25",
      "time": "21:00"
    },
    {
      "id": "2856868",
      "time_obj": "2025-12-10T20:00:00",
      "home_team": "Spanish Town Police",
      "away_team": "Arnett Gardens",
      "handicap": "-1",
      "goal_line": "2.75",
      "time": "21:00"
    },
    {
      "id": "2907984",
      "time_obj": "2025-12-10T20:00:00",
      "home_team": "fraserburgh",
      "away_team": "Keith",
      "handicap": "1.5",
      "goal_line": "3",
      "time": "21:00"
    },
    {
      "id": "2907481",
      "time_obj": "2025-12-10T21:30:00",
      "home_team": "Universitario De Vinto",
      "away_team": "Independiente Petrolero",
      "handicap": "0",
      "goal_line": "3.25",
      "time": "22:30"
    },
    {
      "id": "2884502",
      "time_obj": "2025-12-10T22:00:00",
      "home_team": "Independiente del Valle",
      "away_team": "Liga Dep. Universitaria Quito",
      "handicap": "0.25",
      "goal_line": "2.5",
      "time": "23:00"
    },
    {
      "id": "2892669",
      "time_obj": "2025-12-10T22:00:00",
      "home_team": "Caledonia AIA",
      "away_team": "AC Port Of Spain",
      "handicap": "-0.25",
      "goal_line": "3",
      "time": "23:00"
    },
    {
      "id": "2899769",
      "time_obj": "2025-12-10T23:00:00",
      "home_team": "Huachipato(N)",
      "away_team": "Deportes Limache",
      "handicap": "0.25",
      "goal_line": "2.25",
      "time": "00:00"
    },
    {
      "id": "2906233",
      "time_obj": "2025-12-10T23:00:00",
      "home_team": "Argentino de Merlo",
      "away_team": "Deportivo Armenio",
      "handicap": "0",
      "goal_line": "2",
      "time": "00:00"
    },
    {
      "id": "2907487",
      "time_obj": "2025-12-10T23:00:00",
      "home_team": "Racing Club (W)",
      "away_team": "Belgrano (W)",
      "handicap": "0.25",
      "goal_line": "2",
      "time": "00:00"
    },
    {
      "id": "2906234",
      "time_obj": "2025-12-10T23:30:00",
      "home_team": "Real Pilar",
      "away_team": "Club Atletico Acassuso",
      "handicap": "0.5",
      "goal_line": "1.75",
      "time": "00:30"
    },
    {
      "id": "2907493",
      "time_obj": "2025-12-11T01:00:00",
      "home_team": "Sporting Cristal",
      "away_team": "Cusco FC",
      "handicap": "0.75",
      "goal_line": "2.5",
      "time": "02:00"
    },
    {
      "id": "2908031",
      "time_obj": "2025-12-11T01:00:00",
      "home_team": "Real Espana",
      "away_team": "CD Olimpia",
      "handicap": "0",
      "goal_line": "2.5",
      "time": "02:00"
    }
  ],
  "finished_matches": [
    {
      "id": "2907479",
      "time_obj": "2025-12-09T23:00:00",
      "home_team": "Jorge Wilstermann",
      "away_team": "San Jose de Oruro",
      "score": "2 - 2",
      "handicap": "-0.25",
      "goal_line": "3.25",
      "time": "10/12 00:00"
    },
    {
      "id": "2907980",
      "time_obj": "2025-12-09T23:00:00",
      "home_team": "Sportivo Limpeno (W)",
      "away_team": "Olimpia Asuncion (W)",
      "score": "0 - 4",
      "handicap": "-0.25",
      "goal_line": "2.75",
      "time": "10/12 00:00"
    },
    {
      "id": "2907373",
      "time_obj": "2025-12-09T23:00:00",
      "home_team": "America MG (Youth)(N)",
      "away_team": "Sao Paulo Youth",
      "score": "1 - 2",
      "handicap": "-0.75",
      "goal_line": "2.50",
      "time": "10/12 00:00"
    },
    {
      "id": "2907710",
      "time_obj": "2025-12-09T22:00:00",
      "home_team": "Gremio U20 (W)",
      "away_team": "UDA AL (W) U20",
      "score": "2 - 0",
      "handicap": "5.5",
      "goal_line": "6.75",
      "time": "09/12 23:00"
    },
    {
      "id": "2907708",
      "time_obj": "2025-12-09T21:00:00",
      "home_team": "Sao Paulo U20 (W)",
      "away_team": "Bragantino U20 (W)",
      "score": "1 - 0",
      "handicap": "2.5",
      "goal_line": "3.25",
      "time": "09/12 22:00"
    },
    {
      "id": "2907974",
      "time_obj": "2025-12-09T20:30:00",
      "home_team": "Cerro Porteno (W)",
      "away_team": "Club Guarani (W)",
      "score": "0 - 1",
      "handicap": "-0.75",
      "goal_line": "3.00",
      "time": "09/12 21:30"
    },
    {
      "id": "2861072",
      "time_obj": "2025-12-09T20:00:00",
      "home_team": "Inter Milan",
      "away_team": "Liverpool",
      "score": "0 - 1",
      "handicap": "0.5",
      "goal_line": "2.75",
      "time": "09/12 21:00"
    },
    {
      "id": "2861113",
      "time_obj": "2025-12-09T20:00:00",
      "home_team": "Atalanta",
      "away_team": "Chelsea",
      "score": "2 - 1",
      "handicap": "-0.25",
      "goal_line": "2.50",
      "time": "09/12 21:00"
    },
    {
      "id": "2861124",
      "time_obj": "2025-12-09T20:00:00",
      "home_team": "FC Barcelona",
      "away_team": "Eintracht Frankfurt",
      "score": "2 - 1",
      "handicap": "2.5",
      "goal_line": "4.25",
      "time": "09/12 21:00"
    },
    {
      "id": "2861148",
      "time_obj": "2025-12-09T20:00:00",
      "home_team": "PSV Eindhoven",
      "away_team": "Atletico Madrid",
      "score": "2 - 3",
      "handicap": "-0.25",
      "goal_line": "3.25",
      "time": "09/12 21:00"
    },
    {
      "id": "2861177",
      "time_obj": "2025-12-09T20:00:00",
      "home_team": "Tottenham Hotspur",
      "away_team": "Slavia Praha",
      "score": "3 - 0",
      "handicap": "1.25",
      "goal_line": "2.75",
      "time": "09/12 21:00"
    },
    {
      "id": "2861201",
      "time_obj": "2025-12-09T20:00:00",
      "home_team": "Saint Gilloise(N)",
      "away_team": "Marseille",
      "score": "2 - 3",
      "handicap": "-0.25",
      "goal_line": "2.50",
      "time": "09/12 21:00"
    },
    {
      "id": "2861205",
      "time_obj": "2025-12-09T20:00:00",
      "home_team": "Monaco",
      "away_team": "Galatasaray",
      "score": "1 - 0",
      "handicap": "0.5",
      "goal_line": "3.25",
      "time": "09/12 21:00"
    },
    {
      "id": "2798238",
      "time_obj": "2025-12-09T20:00:00",
      "home_team": "Queens Park Rangers (QPR)",
      "away_team": "Birmingham City",
      "score": "2 - 1",
      "handicap": "0",
      "goal_line": "2.50",
      "time": "09/12 21:00"
    },
    {
      "id": "2797681",
      "time_obj": "2025-12-09T20:00:00",
      "home_team": "Stevenage Borough",
      "away_team": "Cardiff City",
      "score": "0 - 1",
      "handicap": "-0.25",
      "goal_line": "2.25",
      "time": "09/12 21:00"
    },
    {
      "id": "2797682",
      "time_obj": "2025-12-09T20:00:00",
      "home_team": "Reading",
      "away_team": "Peterborough United",
      "score": "1 - 2",
      "handicap": "0.25",
      "goal_line": "2.50",
      "time": "09/12 21:00"
    },
    {
      "id": "2884797",
      "time_obj": "2025-12-09T20:00:00",
      "home_team": "Arsenal (W)",
      "away_team": "FC Twente Enschede (W)",
      "score": "1 - 0",
      "handicap": "2",
      "goal_line": "4.00",
      "time": "09/12 21:00"
    },
    {
      "id": "2884798",
      "time_obj": "2025-12-09T20:00:00",
      "home_team": "Paris Saint Germain (W)",
      "away_team": "Oud-Heverlee Leuven (W)",
      "score": "0 - 0",
      "handicap": "2.25",
      "goal_line": "3.50",
      "time": "09/12 21:00"
    },
    {
      "id": "2884799",
      "time_obj": "2025-12-09T20:00:00",
      "home_team": "Real Madrid (W)",
      "away_team": "VfL Wolfsburg (W)",
      "score": "2 - 0",
      "handicap": "0.5",
      "goal_line": "3.50",
      "time": "09/12 21:00"
    },
    {
      "id": "2906195",
      "time_obj": "2025-12-09T20:00:00",
      "home_team": "Panama U19",
      "away_team": "Honduras U19",
      "score": "3 - 0",
      "handicap": "0.5",
      "goal_line": "2.25",
      "time": "09/12 21:00"
    },
    {
      "id": "2906196",
      "time_obj": "2025-12-09T20:00:00",
      "home_team": "Guatemala U19(N)",
      "away_team": "Costa Rica U19",
      "score": "1 - 2",
      "handicap": "0.75",
      "goal_line": "2.50",
      "time": "09/12 21:00"
    },
    {
      "id": "2798235",
      "time_obj": "2025-12-09T19:45:00",
      "home_team": "Blackburn Rovers",
      "away_team": "Oxford United",
      "score": "1 - 1",
      "handicap": "0.75",
      "goal_line": "2.25",
      "time": "09/12 20:45"
    },
    {
      "id": "2798236",
      "time_obj": "2025-12-09T19:45:00",
      "home_team": "Charlton Athletic",
      "away_team": "Middlesbrough",
      "score": "1 - 2",
      "handicap": "0",
      "goal_line": "2.50",
      "time": "09/12 20:45"
    },
    {
      "id": "2798237",
      "time_obj": "2025-12-09T19:45:00",
      "home_team": "Preston North End",
      "away_team": "Coventry City",
      "score": "1 - 1",
      "handicap": "-0.5",
      "goal_line": "2.50",
      "time": "09/12 20:45"
    },
    {
      "id": "2798239",
      "time_obj": "2025-12-09T19:45:00",
      "home_team": "Sheffield United",
      "away_team": "Norwich City",
      "score": "1 - 1",
      "handicap": "0.75",
      "goal_line": "3.00",
      "time": "09/12 20:45"
    },
    {
      "id": "2798240",
      "time_obj": "2025-12-09T19:45:00",
      "home_team": "Southampton",
      "away_team": "West Bromwich(WBA)",
      "score": "3 - 2",
      "handicap": "0.5",
      "goal_line": "2.75",
      "time": "09/12 20:45"
    },
    {
      "id": "2798241",
      "time_obj": "2025-12-09T19:45:00",
      "home_team": "Watford",
      "away_team": "Sheffield Wednesday",
      "score": "1 - 1",
      "handicap": "1",
      "goal_line": "2.75",
      "time": "09/12 20:45"
    },
    {
      "id": "2798242",
      "time_obj": "2025-12-09T19:45:00",
      "home_team": "Swansea City",
      "away_team": "Portsmouth",
      "score": "1 - 0",
      "handicap": "0.5",
      "goal_line": "2.50",
      "time": "09/12 20:45"
    },
    {
      "id": "2797671",
      "time_obj": "2025-12-09T19:45:00",
      "home_team": "Doncaster Rovers",
      "away_team": "Stockport County",
      "score": "0 - 2",
      "handicap": "0",
      "goal_line": "2.50",
      "time": "09/12 20:45"
    },
    {
      "id": "2797672",
      "time_obj": "2025-12-09T19:45:00",
      "home_team": "Exeter City",
      "away_team": "AFC Wimbledon",
      "score": "1 - 0",
      "handicap": "0.5",
      "goal_line": "2.25",
      "time": "09/12 20:45"
    },
    {
      "id": "2797673",
      "time_obj": "2025-12-09T19:45:00",
      "home_team": "Leyton Orient",
      "away_team": "Luton Town",
      "score": "1 - 1",
      "handicap": "0",
      "goal_line": "2.50",
      "time": "09/12 20:45"
    },
    {
      "id": "2797674",
      "time_obj": "2025-12-09T19:45:00",
      "home_team": "Lincoln City",
      "away_team": "Barnsley",
      "score": "3 - 1",
      "handicap": "0.25",
      "goal_line": "2.50",
      "time": "09/12 20:45"
    },
    {
      "id": "2797675",
      "time_obj": "2025-12-09T19:45:00",
      "home_team": "Mansfield Town",
      "away_team": "Bolton Wanderers",
      "score": "0 - 1",
      "handicap": "-0.5",
      "goal_line": "2.75",
      "time": "09/12 20:45"
    },
    {
      "id": "2797676",
      "time_obj": "2025-12-09T19:45:00",
      "home_team": "Northampton Town",
      "away_team": "Huddersfield Town",
      "score": "1 - 1",
      "handicap": "-0.25",
      "goal_line": "2.25",
      "time": "09/12 20:45"
    },
    {
      "id": "2797680",
      "time_obj": "2025-12-09T19:45:00",
      "home_team": "Wycombe Wanderers",
      "away_team": "Plymouth Argyle",
      "score": "0 - 1",
      "handicap": "0.75",
      "goal_line": "2.50",
      "time": "09/12 20:45"
    },
    {
      "id": "2798775",
      "time_obj": "2025-12-09T19:45:00",
      "home_team": "Barnet",
      "away_team": "Bristol Rovers",
      "score": "4 - 0",
      "handicap": "0.75",
      "goal_line": "2.25",
      "time": "09/12 20:45"
    },
    {
      "id": "2798776",
      "time_obj": "2025-12-09T19:45:00",
      "home_team": "Barrow",
      "away_team": "Tranmere Rovers",
      "score": "0 - 3",
      "handicap": "0",
      "goal_line": "2.25",
      "time": "09/12 20:45"
    },
    {
      "id": "2798777",
      "time_obj": "2025-12-09T19:45:00",
      "home_team": "Bromley",
      "away_team": "Crawley Town",
      "score": "3 - 1",
      "handicap": "0.5",
      "goal_line": "2.75",
      "time": "09/12 20:45"
    },
    {
      "id": "2798778",
      "time_obj": "2025-12-09T19:45:00",
      "home_team": "Cambridge United",
      "away_team": "Chesterfield",
      "score": "1 - 1",
      "handicap": "0.5",
      "goal_line": "2.00",
      "time": "09/12 20:45"
    },
    {
      "id": "2798780",
      "time_obj": "2025-12-09T19:45:00",
      "home_team": "Fleetwood Town",
      "away_team": "Salford City",
      "score": "1 - 1",
      "handicap": "-0.25",
      "goal_line": "2.75",
      "time": "09/12 20:45"
    },
    {
      "id": "2798781",
      "time_obj": "2025-12-09T19:45:00",
      "home_team": "Harrogate Town",
      "away_team": "Accrington Stanley",
      "score": "0 - 2",
      "handicap": "-0.25",
      "goal_line": "2.25",
      "time": "09/12 20:45"
    },
    {
      "id": "2798782",
      "time_obj": "2025-12-09T19:45:00",
      "home_team": "Notts County",
      "away_team": "Milton Keynes Dons",
      "score": "3 - 2",
      "handicap": "-0.25",
      "goal_line": "2.50",
      "time": "09/12 20:45"
    },
    {
      "id": "2798784",
      "time_obj": "2025-12-09T19:45:00",
      "home_team": "Shrewsbury Town",
      "away_team": "Grimsby Town",
      "score": "1 - 1",
      "handicap": "-0.25",
      "goal_line": "2.50",
      "time": "09/12 20:45"
    },
    {
      "id": "2798785",
      "time_obj": "2025-12-09T19:45:00",
      "home_team": "Swindon Town",
      "away_team": "Cheltenham Town",
      "score": "0 - 1",
      "handicap": "1.25",
      "goal_line": "2.75",
      "time": "09/12 20:45"
    },
    {
      "id": "2820214",
      "time_obj": "2025-12-09T19:45:00",
      "home_team": "Leamington",
      "away_team": "AFC Telford United",
      "score": "1 - 3",
      "handicap": "-0.5",
      "goal_line": "2.75",
      "time": "09/12 20:45"
    },
    {
      "id": "2829063",
      "time_obj": "2025-12-09T19:45:00",
      "home_team": "Brentwood Town",
      "away_team": "Cheshunt",
      "score": "2 - 2",
      "handicap": "0.75",
      "goal_line": "3.25",
      "time": "09/12 20:45"
    },
    {
      "id": "2904308",
      "time_obj": "2025-12-09T19:45:00",
      "home_team": "Colchester United",
      "away_team": "West Ham U21",
      "score": "0 - 1",
      "handicap": "0.25",
      "goal_line": "3.00",
      "time": "09/12 20:45"
    },
    {
      "id": "2824035",
      "time_obj": "2025-12-09T19:45:00",
      "home_team": "Briton Ferry Athletic",
      "away_team": "The New Saints",
      "score": "0 - 2",
      "handicap": "-2.25",
      "goal_line": "3.75",
      "time": "09/12 20:45"
    },
    {
      "id": "2824039",
      "time_obj": "2025-12-09T19:45:00",
      "home_team": "Pen-y-Bont FC",
      "away_team": "Barry Town United",
      "score": "1 - 1",
      "handicap": "0.5",
      "goal_line": "2.50",
      "time": "09/12 20:45"
    },
    {
      "id": "2904063",
      "time_obj": "2025-12-09T19:45:00",
      "home_team": "Ayr United",
      "away_team": "Peterhead",
      "score": "2 - 1",
      "handicap": "1.5",
      "goal_line": "3.25",
      "time": "09/12 20:45"
    },
    {
      "id": "2904065",
      "time_obj": "2025-12-09T19:45:00",
      "home_team": "East Kilbride",
      "away_team": "Stranraer",
      "score": "1 - 4",
      "handicap": "1.25",
      "goal_line": "3.00",
      "time": "09/12 20:45"
    },
    {
      "id": "2904067",
      "time_obj": "2025-12-09T19:45:00",
      "home_team": "Ross County",
      "away_team": "Celtic U21",
      "score": "4 - 0",
      "handicap": "2.25",
      "goal_line": "3.75",
      "time": "09/12 20:45"
    },
    {
      "id": "2904069",
      "time_obj": "2025-12-09T19:45:00",
      "home_team": "Arbroath",
      "away_team": "Kelty Hearts",
      "score": "3 - 2",
      "handicap": "1.5",
      "goal_line": "3.25",
      "time": "09/12 20:45"
    },
    {
      "id": "2904072",
      "time_obj": "2025-12-09T19:45:00",
      "home_team": "Forfar Athletic",
      "away_team": "Edinburgh City",
      "score": "1 - 1",
      "handicap": "0",
      "goal_line": "2.75",
      "time": "09/12 20:45"
    },
    {
      "id": "2904073",
      "time_obj": "2025-12-09T19:45:00",
      "home_team": "Stirling Albion",
      "away_team": "Greenock Morton",
      "score": "2 - 2",
      "handicap": "-1.5",
      "goal_line": "3.00",
      "time": "09/12 20:45"
    },
    {
      "id": "2904075",
      "time_obj": "2025-12-09T19:45:00",
      "home_team": "Alloa Athletic",
      "away_team": "Airdrie United",
      "score": "2 - 3",
      "handicap": "0",
      "goal_line": "2.50",
      "time": "09/12 20:45"
    },
    {
      "id": "2904076",
      "time_obj": "2025-12-09T19:45:00",
      "home_team": "Raith Rovers",
      "away_team": "Hamilton Academical",
      "score": "5 - 2",
      "handicap": "2.25",
      "goal_line": "3.50",
      "time": "09/12 20:45"
    },
    {
      "id": "2905993",
      "time_obj": "2025-12-09T19:45:00",
      "home_team": "Stenhousemuir",
      "away_team": "Annan Athletic",
      "score": "2 - 0",
      "handicap": "1",
      "goal_line": "3.00",
      "time": "09/12 20:45"
    },
    {
      "id": "2907706",
      "time_obj": "2025-12-09T19:45:00",
      "home_team": "Witham Town",
      "away_team": "Felixstowe Walton United",
      "score": "2 - 1",
      "handicap": "-0.75",
      "goal_line": "2.75",
      "time": "09/12 20:45"
    },
    {
      "id": "2907690",
      "time_obj": "2025-12-09T19:45:00",
      "home_team": "VCD Athletic",
      "away_team": "Beckenham Town",
      "score": "0 - 2",
      "handicap": "0.75",
      "goal_line": "3.25",
      "time": "09/12 20:45"
    },
    {
      "id": "2907712",
      "time_obj": "2025-12-09T19:45:00",
      "home_team": "Harrow Borough",
      "away_team": "Moneyfields",
      "score": "2 - 3",
      "handicap": "-0.25",
      "goal_line": "3.25",
      "time": "09/12 20:45"
    },
    {
      "id": "2907977",
      "time_obj": "2025-12-09T19:45:00",
      "home_team": "Milton Keynes Irish",
      "away_team": "Flackwell Heath",
      "score": "0 - 3",
      "handicap": "0.25",
      "goal_line": "3.25",
      "time": "09/12 20:45"
    },
    {
      "id": "2907978",
      "time_obj": "2025-12-09T19:45:00",
      "home_team": "Hitchin Town",
      "away_team": "Enfield 1893",
      "score": "6 - 0",
      "handicap": "1.25",
      "goal_line": "3.25",
      "time": "09/12 20:45"
    },
    {
      "id": "2907680",
      "time_obj": "2025-12-09T19:45:00",
      "home_team": "Belper Town",
      "away_team": "Shepshed Dynamo",
      "score": "1 - 1",
      "handicap": "0.75",
      "goal_line": "2.50",
      "time": "09/12 20:45"
    },
    {
      "id": "2907687",
      "time_obj": "2025-12-09T19:45:00",
      "home_team": "Stalybridge Celtic",
      "away_team": "Nantwich Town",
      "score": "3 - 2",
      "handicap": "0.5",
      "goal_line": "2.75",
      "time": "09/12 20:45"
    },
    {
      "id": "2905980",
      "time_obj": "2025-12-09T19:45:00",
      "home_team": "Cowdenbeath",
      "away_team": "Linlithgow Rose",
      "score": "0 - 1",
      "handicap": "-0.5",
      "goal_line": "3.00",
      "time": "09/12 20:45"
    },
    {
      "id": "2843223",
      "time_obj": "2025-12-09T19:45:00",
      "home_team": "Quorn",
      "away_team": "Redditch United",
      "score": "3 - 2",
      "handicap": "0.5",
      "goal_line": "2.50",
      "time": "09/12 20:45"
    },
    {
      "id": "2874263",
      "time_obj": "2025-12-09T19:30:00",
      "home_team": "Zurrieq",
      "away_team": "Santa Lucia",
      "score": "4 - 0",
      "handicap": "-0.25",
      "goal_line": "2.75",
      "time": "09/12 20:30"
    },
    {
      "id": "2907696",
      "time_obj": "2025-12-09T19:30:00",
      "home_team": "USV Hercules",
      "away_team": "Rohda Raalte",
      "score": "2 - 1",
      "handicap": "-1.25",
      "goal_line": "3.25",
      "time": "09/12 20:30"
    },
    {
      "id": "2814319",
      "time_obj": "2025-12-09T19:00:00",
      "home_team": "Genk II(N)",
      "away_team": "Anderlecht II",
      "score": "3 - 2",
      "handicap": "-0.25",
      "goal_line": "3.00",
      "time": "09/12 20:00"
    },
    {
      "id": "2854063",
      "time_obj": "2025-12-09T19:00:00",
      "home_team": "Fulham U21",
      "away_team": "Monchengladbach AM.",
      "score": "0 - 2",
      "handicap": "0.5",
      "goal_line": "3.25",
      "time": "09/12 20:00"
    },
    {
      "id": "2854064",
      "time_obj": "2025-12-09T19:00:00",
      "home_team": "Leicester City U21",
      "away_team": "Nordsjaelland U21",
      "score": "2 - 2",
      "handicap": "-0.75",
      "goal_line": "3.25",
      "time": "09/12 20:00"
    },
    {
      "id": "2907709",
      "time_obj": "2025-12-09T19:00:00",
      "home_team": "Palmeiras U20 (W)",
      "away_team": "Botafogo RJ U20 (W)",
      "score": "0 - 2",
      "handicap": "0",
      "goal_line": "2.75",
      "time": "09/12 20:00"
    },
    {
      "id": "2907976",
      "time_obj": "2025-12-09T18:10:00",
      "home_team": "Hapoel Marmorek U19",
      "away_team": "Hapoel Kfar Shalem U19",
      "score": "3 - 0",
      "handicap": "0.25",
      "goal_line": "2.75",
      "time": "09/12 19:10"
    },
    {
      "id": "2876434",
      "time_obj": "2025-12-09T18:00:00",
      "home_team": "Pyramids FC(N)",
      "away_team": "NBE SC",
      "score": "1 - 6",
      "handicap": "-1.5",
      "goal_line": "2.75",
      "time": "09/12 19:00"
    },
    {
      "id": "2876455",
      "time_obj": "2025-12-09T18:00:00",
      "home_team": "Kahraba Ismailia(N)",
      "away_team": "Zamalek",
      "score": "3 - 3",
      "handicap": "-0.5",
      "goal_line": "2.25",
      "time": "09/12 19:00"
    },
    {
      "id": "2907707",
      "time_obj": "2025-12-09T18:00:00",
      "home_team": "America MG U20 (W)",
      "away_team": "Remo U20 (W)",
      "score": "4 - 0",
      "handicap": "2.25",
      "goal_line": "3.50",
      "time": "09/12 19:00"
    },
    {
      "id": "2907711",
      "time_obj": "2025-12-09T18:00:00",
      "home_team": "Ferroviaria U20 (W)",
      "away_team": "Centro Olimpico U20 (W)",
      "score": "4 - 0",
      "handicap": "4",
      "goal_line": "4.50",
      "time": "09/12 19:00"
    },
    {
      "id": "2861096",
      "time_obj": "2025-12-09T17:45:00",
      "home_team": "Bayern Munchen",
      "away_team": "Sporting CP",
      "score": "3 - 1",
      "handicap": "2",
      "goal_line": "3.50",
      "time": "09/12 18:45"
    },
    {
      "id": "2884796",
      "time_obj": "2025-12-09T17:45:00",
      "home_team": "St. Polten (W)",
      "away_team": "Juventus (W)",
      "score": "0 - 5",
      "handicap": "-2",
      "goal_line": "3.50",
      "time": "09/12 18:45"
    },
    {
      "id": "2904266",
      "time_obj": "2025-12-09T17:00:00",
      "home_team": "Algeria(N)",
      "away_team": "Iraq",
      "score": "2 - 0",
      "handicap": "0.5",
      "goal_line": "2.00",
      "time": "09/12 18:00"
    },
    {
      "id": "2904267",
      "time_obj": "2025-12-09T17:00:00",
      "home_team": "Bahrain(N)",
      "away_team": "Sudan",
      "score": "3 - 1",
      "handicap": "0",
      "goal_line": "1.75",
      "time": "09/12 18:00"
    },
    {
      "id": "2874262",
      "time_obj": "2025-12-09T17:00:00",
      "home_team": "Gudja United",
      "away_team": "Vittoriosa Stars",
      "score": "1 - 0",
      "handicap": "0",
      "goal_line": "2.50",
      "time": "09/12 18:00"
    },
    {
      "id": "2901766",
      "time_obj": "2025-12-09T17:00:00",
      "home_team": "AZ Alkmaar U19",
      "away_team": "Aston Villa U19",
      "score": "2 - 1",
      "handicap": "0.5",
      "goal_line": "3.50",
      "time": "09/12 18:00"
    },
    {
      "id": "2907975",
      "time_obj": "2025-12-09T16:00:00",
      "home_team": "Nouakchott Academie",
      "away_team": "AS Douanes Nouakchott",
      "score": "2 - 4",
      "handicap": "-0.5",
      "goal_line": "2.25",
      "time": "09/12 17:00"
    },
    {
      "id": "2861195",
      "time_obj": "2025-12-09T15:30:00",
      "home_team": "FC Kairat Almaty(N)",
      "away_team": "Olympiakos Piraeus",
      "score": "0 - 1",
      "handicap": "-1.25",
      "goal_line": "2.75",
      "time": "09/12 16:30"
    },
    {
      "id": "2865768",
      "time_obj": "2025-12-09T15:30:00",
      "home_team": "Botev Vratsa",
      "away_team": "PFK Montana",
      "score": "0 - 0",
      "handicap": "0.5",
      "goal_line": "2.00",
      "time": "09/12 16:30"
    },
    {
      "id": "2868748",
      "time_obj": "2025-12-09T15:30:00",
      "home_team": "Standard Sumgayit",
      "away_team": "Mil Mugan",
      "score": "1 - 0",
      "handicap": "0.5",
      "goal_line": "2.25",
      "time": "09/12 16:30"
    },
    {
      "id": "2901765",
      "time_obj": "2025-12-09T15:30:00",
      "home_team": "PAOK Saloniki U19",
      "away_team": "Legia Warszawa U19",
      "score": "1 - 2",
      "handicap": "0.75",
      "goal_line": "3.00",
      "time": "09/12 16:30"
    },
    {
      "id": "2905804",
      "time_obj": "2025-12-09T15:30:00",
      "home_team": "SOL FC Abobo",
      "away_team": "CO Korhogo",
      "score": "1 - 0",
      "handicap": "-0.75",
      "goal_line": "2.00",
      "time": "09/12 16:30"
    },
    {
      "id": "2907700",
      "time_obj": "2025-12-09T15:30:00",
      "home_team": "Al-Ittihad Bahrain U21",
      "away_team": "Al-Riffa U21",
      "score": "1 - 1",
      "handicap": "-0.75",
      "goal_line": "3.50",
      "time": "09/12 16:30"
    },
    {
      "id": "2907874",
      "time_obj": "2025-12-09T15:30:00",
      "home_team": "Busaiteen U21",
      "away_team": "Al Hidd U21",
      "score": "1 - 1",
      "handicap": "-1.5",
      "goal_line": "3.75",
      "time": "09/12 16:30"
    },
    {
      "id": "2907875",
      "time_obj": "2025-12-09T15:30:00",
      "home_team": "Al Hala U21",
      "away_team": "Malkiya U21",
      "score": "0 - 5",
      "handicap": "-1.5",
      "goal_line": "3.75",
      "time": "09/12 16:30"
    },
    {
      "id": "2907876",
      "time_obj": "2025-12-09T15:30:00",
      "home_team": "Al-Muharraq U21",
      "away_team": "Umm Al Hassam U21",
      "score": "0 - 1",
      "handicap": "1",
      "goal_line": "3.75",
      "time": "09/12 16:30"
    },
    {
      "id": "2907878",
      "time_obj": "2025-12-09T15:30:00",
      "home_team": "Al-Ahli Manama U21",
      "away_team": "Sitra U21",
      "score": "2 - 2",
      "handicap": "0.75",
      "goal_line": "2.75",
      "time": "09/12 16:30"
    },
    {
      "id": "2838968",
      "time_obj": "2025-12-09T15:00:00",
      "home_team": "Rio Ave U23",
      "away_team": "Maritimo U23",
      "score": "2 - 1",
      "handicap": "0.25",
      "goal_line": "2.75",
      "time": "09/12 16:00"
    },
    {
      "id": "2838969",
      "time_obj": "2025-12-09T15:00:00",
      "home_team": "Vizela U23",
      "away_team": "Academico Viseu U23",
      "score": "1 - 2",
      "handicap": "-0.25",
      "goal_line": "2.75",
      "time": "09/12 16:00"
    },
    {
      "id": "2895608",
      "time_obj": "2025-12-09T15:00:00",
      "home_team": "Esteghlal Khozestan",
      "away_team": "Kheybar Khorramabad",
      "score": "0 - 1",
      "handicap": "0",
      "goal_line": "1.50",
      "time": "09/12 16:00"
    },
    {
      "id": "2871965",
      "time_obj": "2025-12-09T15:00:00",
      "home_team": "Barcelona U19",
      "away_team": "Eintracht Frankfurt U19",
      "score": "4 - 3",
      "handicap": "1.5",
      "goal_line": "3.75",
      "time": "09/12 16:00"
    },
    {
      "id": "2871967",
      "time_obj": "2025-12-09T15:00:00",
      "home_team": "Inter Milan U19",
      "away_team": "Liverpool U19",
      "score": "5 - 0",
      "handicap": "0",
      "goal_line": "3.25",
      "time": "09/12 16:00"
    },
    {
      "id": "2876413",
      "time_obj": "2025-12-09T15:00:00",
      "home_team": "Pharco",
      "away_team": "El Mokawloon El Arab",
      "score": "3 - 2",
      "handicap": "-0.5",
      "goal_line": "1.75",
      "time": "09/12 16:00"
    },
    {
      "id": "2904260",
      "time_obj": "2025-12-09T14:30:00",
      "home_team": "Egypt(N)",
      "away_team": "Jordan",
      "score": "0 - 3",
      "handicap": "0.75",
      "goal_line": "2.00",
      "time": "09/12 15:30"
    },
    {
      "id": "2904261",
      "time_obj": "2025-12-09T14:30:00",
      "home_team": "United Arab Emirates(N)",
      "away_team": "Kuwait",
      "score": "3 - 1",
      "handicap": "1.25",
      "goal_line": "2.50",
      "time": "09/12 15:30"
    },
    {
      "id": "2907877",
      "time_obj": "2025-12-09T14:30:00",
      "home_team": "De Graafschap U19",
      "away_team": "Sparta Rotterdam U19",
      "score": "0 - 3",
      "handicap": "-1.75",
      "goal_line": "4.25",
      "time": "09/12 15:30"
    },
    {
      "id": "2906194",
      "time_obj": "2025-12-09T14:30:00",
      "home_team": "Nicaragua U19(N)",
      "away_team": "Cuba U19",
      "score": "2 - 1",
      "handicap": "0.75",
      "goal_line": "3.00",
      "time": "09/12 15:30"
    },
    {
      "id": "2906231",
      "time_obj": "2025-12-09T14:30:00",
      "home_team": "Puerto Rico U19(N)",
      "away_team": "El Salvador U19",
      "score": "2 - 2",
      "handicap": "-1.75",
      "goal_line": "2.75",
      "time": "09/12 15:30"
    },
    {
      "id": "2871969",
      "time_obj": "2025-12-09T14:00:00",
      "home_team": "Monaco U19",
      "away_team": "Galatasaray U19",
      "score": "5 - 0",
      "handicap": "2",
      "goal_line": "4.25",
      "time": "09/12 15:00"
    },
    {
      "id": "2907983",
      "time_obj": "2025-12-09T14:00:00",
      "home_team": "Royal Wizards FC (W)",
      "away_team": "Ramatlaohle FC (W)",
      "score": "1 - 2",
      "handicap": "0.25",
      "goal_line": "2.75",
      "time": "09/12 15:00"
    },
    {
      "id": "2907755",
      "time_obj": "2025-12-09T14:00:00",
      "home_team": "SC Internacional U20 (W)",
      "away_team": "Minas Brasilia DF U20 (W)",
      "score": "8 - 0",
      "handicap": "3",
      "goal_line": "4.00",
      "time": "09/12 15:00"
    },
    {
      "id": "2871971",
      "time_obj": "2025-12-09T13:30:00",
      "home_team": "Royale Union Saint Gilloise U19",
      "away_team": "Marseille U19",
      "score": "1 - 4",
      "handicap": "-1",
      "goal_line": "3.25",
      "time": "09/12 14:30"
    },
    {
      "id": "2868744",
      "time_obj": "2025-12-09T13:00:00",
      "home_team": "Araz Nakhchivan",
      "away_team": "FK Kapaz Ganca",
      "score": "2 - 0",
      "handicap": "1",
      "goal_line": "2.50",
      "time": "09/12 14:00"
    },
    {
      "id": "2907867",
      "time_obj": "2025-12-09T13:00:00",
      "home_team": "Mansfield Town Reserve",
      "away_team": "Chesterfield (R)",
      "score": "3 - 0",
      "handicap": "1.75",
      "goal_line": "3.50",
      "time": "09/12 14:00"
    },
    {
      "id": "2871964",
      "time_obj": "2025-12-09T13:00:00",
      "home_team": "Atalanta U19",
      "away_team": "Chelsea FC U19",
      "score": "1 - 3",
      "handicap": "-0.75",
      "goal_line": "3.50",
      "time": "09/12 14:00"
    },
    {
      "id": "2871970",
      "time_obj": "2025-12-09T13:00:00",
      "home_team": "PSV Eindhoven U19",
      "away_team": "Atletico de Madrid U19",
      "score": "3 - 1",
      "handicap": "0",
      "goal_line": "3.25",
      "time": "09/12 14:00"
    },
    {
      "id": "2871972",
      "time_obj": "2025-12-09T13:00:00",
      "home_team": "Tottenham Hotspur U19",
      "away_team": "Slavia Praha U19",
      "score": "9 - 1",
      "handicap": "0.25",
      "goal_line": "4.25",
      "time": "09/12 14:00"
    },
    {
      "id": "2905983",
      "time_obj": "2025-12-09T13:00:00",
      "home_team": "FC Calvary",
      "away_team": "Vipers",
      "score": "0 - 0",
      "handicap": "-2.5",
      "goal_line": "3.50",
      "time": "09/12 14:00"
    },
    {
      "id": "2907662",
      "time_obj": "2025-12-09T13:00:00",
      "home_team": "Cambuur Leeuwarden U21",
      "away_team": "FC Twente/Heracles Academie U21",
      "score": "3 - 1",
      "handicap": "0.25",
      "goal_line": "3.25",
      "time": "09/12 14:00"
    },
    {
      "id": "2907688",
      "time_obj": "2025-12-09T12:55:00",
      "home_team": "Al Ittihad U21",
      "away_team": "Al Hazm U21",
      "score": "4 - 1",
      "handicap": "1",
      "goal_line": "2.75",
      "time": "09/12 13:55"
    },
    {
      "id": "2895605",
      "time_obj": "2025-12-09T12:45:00",
      "home_team": "Shams Azar Qazvin",
      "away_team": "Gol Gohar FC",
      "score": "1 - 1",
      "handicap": "-0.25",
      "goal_line": "1.50",
      "time": "09/12 13:45"
    },
    {
      "id": "2895606",
      "time_obj": "2025-12-09T12:45:00",
      "home_team": "Zob Ahan",
      "away_team": "Tractor S.C.",
      "score": "0 - 0",
      "handicap": "-0.5",
      "goal_line": "1.75",
      "time": "09/12 13:45"
    },
    {
      "id": "2907692",
      "time_obj": "2025-12-09T12:40:00",
      "home_team": "Misr Insurance FC",
      "away_team": "Diamond SC",
      "score": "3 - 2",
      "handicap": "0",
      "goal_line": "2.00",
      "time": "09/12 13:40"
    },
    {
      "id": "2907689",
      "time_obj": "2025-12-09T12:30:00",
      "home_team": "El Shams",
      "away_team": "Banha",
      "score": "1 - 1",
      "handicap": "0.25",
      "goal_line": "2.00",
      "time": "09/12 13:30"
    },
    {
      "id": "2907694",
      "time_obj": "2025-12-09T12:30:00",
      "home_team": "El Obour SC",
      "away_team": "Arish",
      "score": "3 - 2",
      "handicap": "1.5",
      "goal_line": "2.50",
      "time": "09/12 13:30"
    },
    {
      "id": "2907697",
      "time_obj": "2025-12-09T12:30:00",
      "home_team": "Mallawi SC",
      "away_team": "Fayoum",
      "score": "1 - 1",
      "handicap": "-1.5",
      "goal_line": "2.75",
      "time": "09/12 13:30"
    },
    {
      "id": "2871966",
      "time_obj": "2025-12-09T12:30:00",
      "home_team": "Bayern Munchen U19",
      "away_team": "Sporting Lisbon U19",
      "score": "3 - 3",
      "handicap": "-0.5",
      "goal_line": "3.50",
      "time": "09/12 13:30"
    },
    {
      "id": "2907862",
      "time_obj": "2025-12-09T12:30:00",
      "home_team": "Ahli Bank (W)",
      "away_team": "FC Masar (W)",
      "score": "0 - 8",
      "handicap": "-1.75",
      "goal_line": "3.25",
      "time": "09/12 13:30"
    },
    {
      "id": "2860627",
      "time_obj": "2025-12-09T12:15:00",
      "home_team": "Buriram United",
      "away_team": "Gangwon FC",
      "score": "2 - 2",
      "handicap": "0.25",
      "goal_line": "1.75",
      "time": "09/12 13:15"
    },
    {
      "id": "2860628",
      "time_obj": "2025-12-09T12:15:00",
      "home_team": "Johor Darul Takzim",
      "away_team": "Shanghai Port",
      "score": "0 - 0",
      "handicap": "1.5",
      "goal_line": "3.25",
      "time": "09/12 13:15"
    },
    {
      "id": "2839037",
      "time_obj": "2025-12-09T12:00:00",
      "home_team": "Santa Clara U23",
      "away_team": "Estrela FC U23",
      "score": "2 - 1",
      "handicap": "0.75",
      "goal_line": "2.50",
      "time": "09/12 13:00"
    },
    {
      "id": "2907663",
      "time_obj": "2025-12-09T12:00:00",
      "home_team": "Perseden Denpasar",
      "away_team": "Waanal Brothers",
      "score": "2 - 0",
      "handicap": "1",
      "goal_line": "3.00",
      "time": "09/12 13:00"
    },
    {
      "id": "2907705",
      "time_obj": "2025-12-09T12:00:00",
      "home_team": "First Bank FC",
      "away_team": "Abeokuta Stormers",
      "score": "1 - 1",
      "handicap": "0.25",
      "goal_line": "2.25",
      "time": "09/12 13:00"
    },
    {
      "id": "2907691",
      "time_obj": "2025-12-09T12:00:00",
      "home_team": "Al Salt Reserves",
      "away_team": "Sama Al Sarhan Reserves",
      "score": "2 - 2",
      "handicap": "0",
      "goal_line": "3.00",
      "time": "09/12 13:00"
    },
    {
      "id": "2907693",
      "time_obj": "2025-12-09T12:00:00",
      "home_team": "Al-Hussein SC Reserve",
      "away_team": "Shabab Al Ordon Reserves",
      "score": "0 - 0",
      "handicap": "0.5",
      "goal_line": "3.00",
      "time": "09/12 13:00"
    },
    {
      "id": "2907704",
      "time_obj": "2025-12-09T11:55:00",
      "home_team": "Ethio Electric FC (W)",
      "away_team": "Bole Sub City (W)",
      "score": "1 - 2",
      "handicap": "2.5",
      "goal_line": "3.00",
      "time": "09/12 12:55"
    },
    {
      "id": "2907861",
      "time_obj": "2025-12-09T11:40:00",
      "home_team": "Ferdosi Samen",
      "away_team": "Pas",
      "score": "1 - 0",
      "handicap": "0.5",
      "goal_line": "1.50",
      "time": "09/12 12:40"
    },
    {
      "id": "2907695",
      "time_obj": "2025-12-09T11:30:00",
      "home_team": "Arka Alborz",
      "away_team": "Shahin Bandar Anzali",
      "score": "0 - 0",
      "handicap": "0",
      "goal_line": "1.50",
      "time": "09/12 12:30"
    },
    {
      "id": "2907685",
      "time_obj": "2025-12-09T11:30:00",
      "home_team": "Balestier Khalsa FC U23",
      "away_team": "Young Lions U23",
      "score": "0 - 4",
      "handicap": "-3.5",
      "goal_line": "5.00",
      "time": "09/12 12:30"
    },
    {
      "id": "2907841",
      "time_obj": "2025-12-09T11:10:00",
      "home_team": "All Stars FC (W)",
      "away_team": "Super Strikers Ladies (W)",
      "score": "1 - 2",
      "handicap": "0",
      "goal_line": "2.75",
      "time": "09/12 12:10"
    },
    {
      "id": "2907842",
      "time_obj": "2025-12-09T11:10:00",
      "home_team": "Central University of Technology (W)",
      "away_team": "4800 Ladies FC (W)",
      "score": "2 - 1",
      "handicap": "-1",
      "goal_line": "3.00",
      "time": "09/12 12:10"
    },
    {
      "id": "2907847",
      "time_obj": "2025-12-09T11:05:00",
      "home_team": "Setaregan Sorkh",
      "away_team": "Aseman Golestan",
      "score": "1 - 0",
      "handicap": "0",
      "goal_line": "1.75",
      "time": "09/12 12:05"
    },
    {
      "id": "2838967",
      "time_obj": "2025-12-09T11:00:00",
      "home_team": "Leixoes U23",
      "away_team": "Gil Vicente U23",
      "score": "1 - 1",
      "handicap": "0.25",
      "goal_line": "2.75",
      "time": "09/12 12:00"
    },
    {
      "id": "2907660",
      "time_obj": "2025-12-09T11:00:00",
      "home_team": "Aseb Sports Club",
      "away_team": "Sunrise AC",
      "score": "0 - 3",
      "handicap": "0.5",
      "goal_line": "3.25",
      "time": "09/12 12:00"
    },
    {
      "id": "2907754",
      "time_obj": "2025-12-09T11:00:00",
      "home_team": "Langsning SC",
      "away_team": "Nongkseh SCC",
      "score": "2 - 2",
      "handicap": "0.25",
      "goal_line": "2.75",
      "time": "09/12 12:00"
    },
    {
      "id": "2844697",
      "time_obj": "2025-12-09T10:10:00",
      "home_team": "FC Chernigiv",
      "away_team": "Probiy Horodenka",
      "score": "3 - 0",
      "handicap": "0.5",
      "goal_line": "2.25",
      "time": "09/12 11:10"
    },
    {
      "id": "2860625",
      "time_obj": "2025-12-09T10:00:00",
      "home_team": "Machida Zelvia",
      "away_team": "Ulsan HD FC",
      "score": "3 - 1",
      "handicap": "1",
      "goal_line": "2.50",
      "time": "09/12 11:00"
    },
    {
      "id": "2860626",
      "time_obj": "2025-12-09T10:00:00",
      "home_team": "Vissel Kobe",
      "away_team": "Chengdu Rongcheng FC",
      "score": "2 - 2",
      "handicap": "1",
      "goal_line": "2.50",
      "time": "09/12 11:00"
    },
    {
      "id": "2907840",
      "time_obj": "2025-12-09T08:40:00",
      "home_team": "Diepkloof FC  (W)",
      "away_team": "Ramatlaohle FC (W)",
      "score": "0 - 2",
      "handicap": "0.25",
      "goal_line": "3.25",
      "time": "09/12 09:40"
    },
    {
      "id": "2905984",
      "time_obj": "2025-12-09T08:30:00",
      "home_team": "Abahani Limited",
      "away_team": "Brothers Union",
      "score": "0 - 1",
      "handicap": "0.75",
      "goal_line": "2.50",
      "time": "09/12 09:30"
    },
    {
      "id": "2907664",
      "time_obj": "2025-12-09T08:00:00",
      "home_team": "Persebata Lembata",
      "away_team": "Persekabpas Pasuruan",
      "score": "0 - 1",
      "handicap": "-1",
      "goal_line": "2.75",
      "time": "09/12 09:00"
    },
    {
      "id": "2907665",
      "time_obj": "2025-12-09T08:00:00",
      "home_team": "PSGC Ciamis",
      "away_team": "Tri Brata Rafflesia FC",
      "score": "3 - 1",
      "handicap": "0.5",
      "goal_line": "2.25",
      "time": "09/12 09:00"
    },
    {
      "id": "2907651",
      "time_obj": "2025-12-09T08:00:00",
      "home_team": "Assam Police",
      "away_team": "Numaligarh Refinery",
      "score": "0 - 2",
      "handicap": "0.5",
      "goal_line": "3.25",
      "time": "09/12 09:00"
    },
    {
      "id": "2871968",
      "time_obj": "2025-12-09T07:00:00",
      "home_team": "Kairat Almaty U19",
      "away_team": "Olympiakos Piraeus U19",
      "score": "2 - 0",
      "handicap": "-0.75",
      "goal_line": "3.25",
      "time": "09/12 08:00"
    },
    {
      "id": "2907678",
      "time_obj": "2025-12-09T06:55:00",
      "home_team": "Ethiopia Nigd Bank (W)",
      "away_team": "Dire Dawa (W)",
      "score": "1 - 0",
      "handicap": "3.5",
      "goal_line": "4.00",
      "time": "09/12 07:55"
    }
  ]
}